MANIFEST.in
README.rst
setup.py
bookbinder/__init__.py
bookbinder/attributes.py
bookbinder/bookfile.py
bookbinder/epub.py
bookbinder/gdrive.py
bookbinder/metadata.py
bookbinder/sanitizer.py
bookbinder/stash.py
bookbinder/templates.py
bookbinder/toc.py
bookbinder.egg-info/PKG-INFO
bookbinder.egg-info/SOURCES.txt
bookbinder.egg-info/dependency_links.txt
bookbinder.egg-info/entry_points.txt
bookbinder.egg-info/not-zip-safe
bookbinder.egg-info/requires.txt
bookbinder.egg-info/top_level.txt
bookbinder/templates/content.opf