Metadata-Version: 1.1
Name: bookbinder
Version: 0.1.9
Summary: ePub generation from Google Documents
Home-page: https://github.com/canpolat/bookbinder
Author: Eren Inan Canpolat
Author-email: eren.canpolat@gmail.com
License: UNKNOWN
Platform: UNKNOWN
Classifier: Development Status :: 2 - Pre-Alpha
Classifier: Environment :: Console
Classifier: License :: OSI Approved :: GNU General Public License v3 or later (GPLv3+)
Classifier: Natural Language :: English
Classifier: Programming Language :: Python :: 2.7
